clitools/__init__.py
clitools/geoslurper.py
geoslurp/__init__.py
geoslurp/config/__init__.py
geoslurp/config/catalogue.py
geoslurp/config/localsettings.py
geoslurp/config/slurplogger.py
geoslurp/datapull/__init__.py
geoslurp/datapull/cds.py
geoslurp/datapull/crawler.py
geoslurp/datapull/ftp.py
geoslurp/datapull/geodesyunr.py
geoslurp/datapull/github.py
geoslurp/datapull/http.py
geoslurp/datapull/icgem.py
geoslurp/datapull/motu.py
geoslurp/datapull/rsync.py
geoslurp/datapull/sftp.py
geoslurp/datapull/thredds.py
geoslurp/datapull/uri.py
geoslurp/datapull/webdav.py
geoslurp/dataset/CSVBase.py
geoslurp/dataset/OGRBase.py
geoslurp/dataset/RasterBase.py
geoslurp/dataset/__init__.py
geoslurp/dataset/cdsbase.py
geoslurp/dataset/dataSetBase.py
geoslurp/dataset/datasetgeneric.py
geoslurp/dataset/era5.py
geoslurp/dataset/motuGridsBase.py
geoslurp/dataset/pandasbase.py
geoslurp/dataset/snrei.py
geoslurp/dataset/xarraybase.py
geoslurp/db/__init__.py
geoslurp/db/connector.py
geoslurp/db/connectorbase.py
geoslurp/db/exporter.py
geoslurp/db/geoslurpdb.py
geoslurp/db/inventory.py
geoslurp/db/settings.py
geoslurp/db/tabletools.py
geoslurp/dbfunc/__init__.py
geoslurp/dbfunc/dbfunc.py
geoslurp/dbfunc/maskgeom.py
geoslurp/dbfunc/radsfuncs.py
geoslurp/dbfunc/readfile.py
geoslurp/discover/__init__.py
geoslurp/discover/earthmodels/__init__.py
geoslurp/discover/earthmodels/getlove.py
geoslurp/discover/fesom/__init__.py
geoslurp/discover/fesom/extractprofiles.py
geoslurp/discover/fesom/fesomQuery.py
geoslurp/discover/generic/__init__.py
geoslurp/discover/generic/getTableData.py
geoslurp/discover/generic/regexQuery.py
geoslurp/discover/gravity/__init__.py
geoslurp/discover/gravity/graceQuery.py
geoslurp/discover/gravity/gravQuery.py
geoslurp/discover/gravity/staticQuery.py
geoslurp/discover/oceanobs/__init__.py
geoslurp/discover/oceanobs/argoProfiles.py
geoslurp/discover/oceanobs/argoQuery.py
geoslurp/discover/oceanobs/awipiesQuery.py
geoslurp/discover/oceanobs/coraQuery.py
geoslurp-2.2.1.dist-info/LICENSE
geoslurp-2.2.1.dist-info/METADATA
geoslurp-2.2.1.dist-info/WHEEL
geoslurp-2.2.1.dist-info/top_level.txt
geoslurp-2.2.1.dist-info/RECORD
