Metadata-Version: 2.1
Name: geoslurp
Version: 2.2.1
Summary: Python postgreSQL-PostGIS client for managing earth science datasets
Home-page: https://github.com/strawpants/geoslurp
Author: Roelof Rietbroek
Author-email: roelof@wobbly.earth
Classifier: Programming Language :: Python :: 3
Classifier: License :: OSI Approved :: GNU Lesser General Public License v3 (LGPLv3)
Classifier: Operating System :: POSIX :: Linux
Classifier: Topic :: Scientific/Engineering
Classifier: Intended Audience :: Science/Research
Classifier: Development Status :: 4 - Beta
License-File: LICENSE
Requires-Dist: numpy
Requires-Dist: SQLAlchemy
Requires-Dist: pycurl
Requires-Dist: cryptography
Requires-Dist: PyYAML
Requires-Dist: lxml
Requires-Dist: keyring
Requires-Dist: pandas
Requires-Dist: motuclient
Requires-Dist: netCDF4
Requires-Dist: GDAL
Requires-Dist: Shapely
Requires-Dist: GeoAlchemy2
Requires-Dist: psycopg2
Provides-Extra: sh
Requires-Dist: pyshtools ; extra == 'sh'
